{
  "fondo": {
    "nombre": "BBVAEUR",
    "url": "https://portal.bbva.mx/siabinternet/Repositorio/import/doctos/analisis/00004357.pdf",
    "razon_social": {
      "valor": "Fondo BBVA Bancomer Deuda Inversión en Moneda Extranjera, S.A. de C.V., Fondo de Inversión en Instrumentos de Deuda"
    },
    "fecha_autorizacion": {
      "valor": "20181026"
    },
    "tipo": {
      "valor": "Deuda",
      "id": 100
    },
    "administradora": {
      "nombre": "BBVA Bancomer Gestión, S.A. de C.V. Sociedad Operadora de Fondos de Inversión, Grupo Financiero BBVA Bancomer.",
      "valor": 6
    },
    "horizonte_inversion": {
      "valor": "Corto plazo"
    },
    "liquidez": {
      "valor": "Diaria"
    },
    "permanencia": {
      "valor": "No aplica"
    },
    "calificacion_mercado": {
      "valor": "AAA/7"
    },
    "director": {
      "valor": "Erick Noel Rodríguez Jimarez"
    },
    "vigente": 1,
    "categoria": {
      "valor": "Corto Plazo Moneda Extranjera - IDCPME"
    },
    "horario_cierre": {
      "valor": "13:00 horas"
    },
    "campos_faltantes": [],
    "serie": [
      {
        "nombre": "B",
        "monto_minimo": {
          "valor": "1 acción"
        },
        "monto_maximo": {
          "valor": null
        },
        "comision_cliente": {
          "valor": "No aplica"
        },
        "comision_fondo": {
          "valor": "2.14"
        },
        "posibles_adquirientes": {
          "valor": "Personas Físicas"
        },
        "vigente": 1,
        "clave_BMV": "BBVAEURB",
        "campos_faltantes": []
      },
      {
        "nombre": "C",
        "monto_minimo": {
          "valor": "$500,000.00"
        },
        "monto_maximo": {
          "valor": null
        },
        "comision_cliente": {
          "valor": "No aplica"
        },
        "comision_fondo": {
          "valor": "2.13"
        },
        "posibles_adquirientes": {
          "valor": "Personas Físicas"
        },
        "vigente": 1,
        "clave_BMV": "BBVAEURC",
        "campos_faltantes": []
      },
      {
        "nombre": "E",
        "monto_minimo": {
          "valor": "No aplica"
        },
        "monto_maximo": {
          "valor": null
        },
        "comision_cliente": {
          "valor": "No aplica"
        },
        "comision_fondo": {
          "valor": "0.40"
        },
        "posibles_adquirientes": {
          "valor": "Personas Morales"
        },
        "vigente": 1,
        "clave_BMV": "BBVAEURE",
        "campos_faltantes": []
      },
      {
        "nombre": "F",
        "monto_minimo": {
          "valor": "No aplica"
        },
        "monto_maximo": {
          "valor": null
        },
        "comision_cliente": {
          "valor": "No aplica"
        },
        "comision_fondo": {
          "valor": "0.01"
        },
        "posibles_adquirientes": {
          "valor": "Fondos de Inversión"
        },
        "vigente": 1,
        "clave_BMV": "BBVAEURF",
        "campos_faltantes": []
      },
      {
        "nombre": "GB",
        "monto_minimo": {
          "valor": "No aplica"
        },
        "monto_maximo": {
          "valor": null
        },
        "comision_cliente": {
          "valor": "No aplica"
        },
        "comision_fondo": {
          "valor": "0.77"
        },
        "posibles_adquirientes": {
          "valor": "Empleados y jubilados del grupo financiero"
        },
        "vigente": 1,
        "clave_BMV": "BBVAEURGB",
        "campos_faltantes": []
      },
      {
        "nombre": "GPF",
        "monto_minimo": {
          "valor": "No aplica"
        },
        "monto_maximo": {
          "valor": null
        },
        "comision_cliente": {
          "valor": "No aplica"
        },
        "comision_fondo": {
          "valor": "0.01"
        },
        "posibles_adquirientes": {
          "valor": "Gestión Portafolios Físicas"
        },
        "vigente": 1,
        "clave_BMV": "BBVAEURGPF",
        "campos_faltantes": []
      },
      {
        "nombre": "NC",
        "monto_minimo": {
          "valor": "No aplica"
        },
        "monto_maximo": {
          "valor": null
        },
        "comision_cliente": {
          "valor": "No aplica"
        },
        "comision_fondo": {
          "valor": "0.35"
        },
        "posibles_adquirientes": {
          "valor": "Personas morales no sujetas a retención"
        },
        "vigente": 1,
        "clave_BMV": "BBVAEURNC",
        "campos_faltantes": []
      },
      {
        "nombre": "P",
        "monto_minimo": {
          "valor": "$1,000,000.00"
        },
        "monto_maximo": {
          "valor": null
        },
        "comision_cliente": {
          "valor": "No aplica"
        },
        "comision_fondo": {
          "valor": "1.84"
        },
        "posibles_adquirientes": {
          "valor": "Personas Físicas"
        },
        "vigente": 1,
        "clave_BMV": "BBVAEURP",
        "campos_faltantes": []
      },
      {
        "nombre": "PV",
        "monto_minimo": {
          "valor": "$15,000,000.00"
        },
        "monto_maximo": {
          "valor": null
        },
        "comision_cliente": {
          "valor": "No aplica"
        },
        "comision_fondo": {
          "valor": "1.53"
        },
        "posibles_adquirientes": {
          "valor": "Personas Físicas"
        },
        "vigente": 1,
        "clave_BMV": "BBVAEURPV",
        "campos_faltantes": []
      },
      {
        "nombre": "UHN",
        "monto_minimo": {
          "valor": "$100,000,000.00"
        },
        "monto_maximo": {
          "valor": null
        },
        "comision_cliente": {
          "valor": "No aplica"
        },
        "comision_fondo": {
          "valor": "1.24"
        },
        "posibles_adquirientes": {
          "valor": "Personas Físicas"
        },
        "vigente": 1,
        "clave_BMV": "BBVAEURUHN",
        "campos_faltantes": []
      }
    ]
  }
}