{
  "fondo": {
    "nombre": "BMERLIQ",
    "url": "https://portal.bbva.mx/siabinternet/Repositorio/import/doctos/analisis/00004612.pdf",
    "razon_social": {
      "valor": "Fondo BBVA Bancomer Deuda Líquido, S.A. de C.V. Fondo de Inversión en Instrumentos de Deuda"
    },
    "fecha_autorizacion": {
      "valor": "20181002"
    },
    "tipo": {
      "valor": "Deuda",
      "id": 100
    },
    "administradora": {
      "nombre": "BBVA Bancomer Gestión, S.A. de C.V. Sociedad Operadora de Fondos de Inversión, Grupo Financiero BBVA Bancomer.",
      "valor": 6
    },
    "horizonte_inversion": {
      "valor": "Corto plazo"
    },
    "liquidez": {
      "valor": "Diaria"
    },
    "permanencia": {
      "valor": "No aplica"
    },
    "calificacion_mercado": {
      "valor": "AAA/1"
    },
    "director": {
      "valor": "Erick Noel Rodríguez Jimarez"
    },
    "vigente": 1,
    "categoria": {
      "valor": "Corto Plazo - IDCP"
    },
    "horario_cierre": {
      "valor": "13:30 hrs"
    },
    "campos_faltantes": [],
    "serie": [
      {
        "nombre": "B1",
        "monto_minimo": {
          "valor": "1 acción"
        },
        "monto_maximo": {
          "valor": null
        },
        "comision_cliente": {
          "valor": "No aplica"
        },
        "comision_fondo": {
          "valor": "2.32"
        },
        "posibles_adquirientes": {
          "valor": "Personas Físicas"
        },
        "vigente": 1,
        "clave_BMV": "BMERLIQB1",
        "campos_faltantes": []
      },
      {
        "nombre": "B2",
        "monto_minimo": {
          "valor": "$100,000.00"
        },
        "monto_maximo": {
          "valor": null
        },
        "comision_cliente": {
          "valor": "No aplica"
        },
        "comision_fondo": {
          "valor": "2.30"
        },
        "posibles_adquirientes": {
          "valor": "Personas Físicas"
        },
        "vigente": 1,
        "clave_BMV": "BMERLIQB2",
        "campos_faltantes": []
      },
      {
        "nombre": "B3",
        "monto_minimo": {
          "valor": "$200,000.00"
        },
        "monto_maximo": {
          "valor": null
        },
        "comision_cliente": {
          "valor": "No aplica"
        },
        "comision_fondo": {
          "valor": "2.26"
        },
        "posibles_adquirientes": {
          "valor": "Personas Físicas"
        },
        "vigente": 1,
        "clave_BMV": "BMERLIQB3",
        "campos_faltantes": []
      },
      {
        "nombre": "B4",
        "monto_minimo": {
          "valor": "$300,000.00"
        },
        "monto_maximo": {
          "valor": null
        },
        "comision_cliente": {
          "valor": "No aplica"
        },
        "comision_fondo": {
          "valor": "2.14"
        },
        "posibles_adquirientes": {
          "valor": "Personas Físicas"
        },
        "vigente": 1,
        "clave_BMV": "BMERLIQB4",
        "campos_faltantes": []
      },
      {
        "nombre": "C",
        "monto_minimo": {
          "valor": "$500,000.00"
        },
        "monto_maximo": {
          "valor": null
        },
        "comision_cliente": {
          "valor": "No aplica"
        },
        "comision_fondo": {
          "valor": "1.84"
        },
        "posibles_adquirientes": {
          "valor": "Personas Físicas"
        },
        "vigente": 1,
        "clave_BMV": "BMERLIQC",
        "campos_faltantes": []
      },
      {
        "nombre": "GB",
        "monto_minimo": {
          "valor": "No aplica"
        },
        "monto_maximo": {
          "valor": null
        },
        "comision_cliente": {
          "valor": "No aplica"
        },
        "comision_fondo": {
          "valor": "0.42"
        },
        "posibles_adquirientes": {
          "valor": "Empleados y jubilados del grupo financiero"
        },
        "vigente": 1,
        "clave_BMV": "BMERLIQGB",
        "campos_faltantes": []
      },
      {
        "nombre": "GPF",
        "monto_minimo": {
          "valor": "No aplica"
        },
        "monto_maximo": {
          "valor": null
        },
        "comision_cliente": {
          "valor": "No aplica"
        },
        "comision_fondo": {
          "valor": "0.01"
        },
        "posibles_adquirientes": {
          "valor": "Gestión Portafolios Físicas"
        },
        "vigente": 1,
        "clave_BMV": "BMERLIQGPF",
        "campos_faltantes": []
      },
      {
        "nombre": "P",
        "monto_minimo": {
          "valor": "$1,000,000.00"
        },
        "monto_maximo": {
          "valor": null
        },
        "comision_cliente": {
          "valor": "No aplica"
        },
        "comision_fondo": {
          "valor": "1.67"
        },
        "posibles_adquirientes": {
          "valor": "Personas Físicas"
        },
        "vigente": 1,
        "clave_BMV": "BMERLIQP",
        "campos_faltantes": []
      },
      {
        "nombre": "PV",
        "monto_minimo": {
          "valor": "$15,000,000.00"
        },
        "monto_maximo": {
          "valor": null
        },
        "comision_cliente": {
          "valor": "No aplica"
        },
        "comision_fondo": {
          "valor": "1.31"
        },
        "posibles_adquirientes": {
          "valor": "Personas Físicas"
        },
        "vigente": 1,
        "clave_BMV": "BMERLIQPV",
        "campos_faltantes": []
      }
    ]
  }
}